[
  {
    "result": 1,
    "cur_unit": "AED",
    "ttb": "394.71",
    "tts": "402.68",
    "deal_bas_r": "398.7",
    "bkpr": "398",
    "yy_efee_r": "0",
    "ten_dd_efee_r": "0",
    "kftc_bkpr": "398",
    "kftc_deal_bas_r": "398.7",
    "cur_nm": "아랍에미리트 디르함"
  },
  {
    "result": 1,
    "cur_unit": "AUD",
    "ttb": "1,020.41",
    "tts": "1,041.02",
    "deal_bas_r": "1,030.72",
    "bkpr": "1,030",
    "yy_efee_r": "0",
    "ten_dd_efee_r": "0",
    "kftc_bkpr": "1,030",
    "kftc_deal_bas_r": "1,030.72",
    "cur_nm": "호주 달러"
  },
  {
    "result": 1,
    "cur_unit": "BHD",
    "ttb": "3,843.21",
    "tts": "3,920.86",
    "deal_bas_r": "3,882.04",
    "bkpr": "3,882",
    "yy_efee_r": "0",
    "ten_dd_efee_r": "0",
    "kftc_bkpr": "3,882",
    "kftc_deal_bas_r": "3,882.04",
    "cur_nm": "바레인 디나르"
  },
  {
    "result": 1,
    "cur_unit": "BND",
    "ttb": "1,135.57",
    "tts": "1,158.52",
    "deal_bas_r": "1,147.05",
    "bkpr": "1,147",
    "yy_efee_r": "0",
    "ten_dd_efee_r": "0",
    "kftc_bkpr": "1,147",
    "kftc_deal_bas_r": "1,147.05",
    "cur_nm": "브루나이 달러"
  },
  {
    "result": 1,
    "cur_unit": "CAD",
    "ttb": "1,060.03",
    "tts": "1,081.44",
    "deal_bas_r": "1,070.74",
    "bkpr": "1,070",
    "yy_efee_r": "0",
    "ten_dd_efee_r": "0",
    "kftc_bkpr": "1,070",
    "kftc_deal_bas_r": "1,070.74",
    "cur_nm": "캐나다 달러"
  },
  {
    "result": 1,
    "cur_unit": "CHF",
    "ttb": "1,853.08",
    "tts": "1,890.51",
    "deal_bas_r": "1,871.8",
    "bkpr": "1,871",
    "yy_efee_r": "0",
    "ten_dd_efee_r": "0",
    "kftc_bkpr": "1,871",
    "kftc_deal_bas_r": "1,871.8",
    "cur_nm": "스위스 프랑"
  },
  {
    "result": 1,
    "cur_unit": "CNH",
    "ttb": "210.69",
    "tts": "214.94",
    "deal_bas_r": "212.82",
    "bkpr": "212",
    "yy_efee_r": "0",
    "ten_dd_efee_r": "0",
    "kftc_bkpr": "212",
    "kftc_deal_bas_r": "212.82",
    "cur_nm": "위안화"
  },
  {
    "result": 1,
    "cur_unit": "DKK",
    "ttb": "225.39",
    "tts": "229.94",
    "deal_bas_r": "227.67",
    "bkpr": "227",
    "yy_efee_r": "0",
    "ten_dd_efee_r": "0",
    "kftc_bkpr": "227",
    "kftc_deal_bas_r": "227.67",
    "cur_nm": "덴마아크 크로네"
  },
  {
    "result": 1,
    "cur_unit": "EUR",
    "ttb": "1,684.07",
    "tts": "1,718.1",
    "deal_bas_r": "1,701.09",
    "bkpr": "1,701",
    "yy_efee_r": "0",
    "ten_dd_efee_r": "0",
    "kftc_bkpr": "1,701",
    "kftc_deal_bas_r": "1,701.09",
    "cur_nm": "유로"
  },
  {
    "result": 1,
    "cur_unit": "GBP",
    "ttb": "1,936.56",
    "tts": "1,975.69",
    "deal_bas_r": "1,956.13",
    "bkpr": "1,956",
    "yy_efee_r": "0",
    "ten_dd_efee_r": "0",
    "kftc_bkpr": "1,956",
    "kftc_deal_bas_r": "1,956.13",
    "cur_nm": "영국 파운드"
  },
  {
    "result": 1,
    "cur_unit": "HKD",
    "ttb": "185.76",
    "tts": "189.51",
    "deal_bas_r": "187.64",
    "bkpr": "187",
    "yy_efee_r": "0",
    "ten_dd_efee_r": "0",
    "kftc_bkpr": "187",
    "kftc_deal_bas_r": "187.64",
    "cur_nm": "홍콩 달러"
  },
  {
    "result": 1,
    "cur_unit": "IDR(100)",
    "ttb": "8.6",
    "tts": "8.77",
    "deal_bas_r": "8.69",
    "bkpr": "8",
    "yy_efee_r": "0",
    "ten_dd_efee_r": "0",
    "kftc_bkpr": "8",
    "kftc_deal_bas_r": "8.69",
    "cur_nm": "인도네시아 루피아"
  },
  {
    "result": 1,
    "cur_unit": "JPY(100)",
    "ttb": "919.98",
    "tts": "938.57",
    "deal_bas_r": "929.28",
    "bkpr": "929",
    "yy_efee_r": "0",
    "ten_dd_efee_r": "0",
    "kftc_bkpr": "929",
    "kftc_deal_bas_r": "929.28",
    "cur_nm": "일본 옌"
  },
  {
    "result": 1,
    "cur_unit": "KRW",
    "ttb": "0",
    "tts": "0",
    "deal_bas_r": "1",
    "bkpr": "1",
    "yy_efee_r": "0",
    "ten_dd_efee_r": "0",
    "kftc_bkpr": "1",
    "kftc_deal_bas_r": "1",
    "cur_nm": "한국 원"
  },
  {
    "result": 1,
    "cur_unit": "KWD",
    "ttb": "4,738.09",
    "tts": "4,833.8",
    "deal_bas_r": "4,785.95",
    "bkpr": "4,785",
    "yy_efee_r": "0",
    "ten_dd_efee_r": "0",
    "kftc_bkpr": "4,785",
    "kftc_deal_bas_r": "4,785.95",
    "cur_nm": "쿠웨이트 디나르"
  },
  {
    "result": 1,
    "cur_unit": "MYR",
    "ttb": "367.42",
    "tts": "374.85",
    "deal_bas_r": "371.14",
    "bkpr": "371",
    "yy_efee_r": "0",
    "ten_dd_efee_r": "0",
    "kftc_bkpr": "371",
    "kftc_deal_bas_r": "371.14",
    "cur_nm": "말레이지아 링기트"
  },
  {
    "result": 1,
    "cur_unit": "NOK",
    "ttb": "149.84",
    "tts": "152.87",
    "deal_bas_r": "151.36",
    "bkpr": "151",
    "yy_efee_r": "0",
    "ten_dd_efee_r": "0",
    "kftc_bkpr": "151",
    "kftc_deal_bas_r": "151.36",
    "cur_nm": "노르웨이 크로네"
  },
  {
    "result": 1,
    "cur_unit": "NZD",
    "ttb": "854.18",
    "tts": "871.43",
    "deal_bas_r": "862.81",
    "bkpr": "862",
    "yy_efee_r": "0",
    "ten_dd_efee_r": "0",
    "kftc_bkpr": "862",
    "kftc_deal_bas_r": "862.81",
    "cur_nm": "뉴질랜드 달러"
  },
  {
    "result": 1,
    "cur_unit": "SAR",
    "ttb": "386.31",
    "tts": "394.12",
    "deal_bas_r": "390.22",
    "bkpr": "390",
    "yy_efee_r": "0",
    "ten_dd_efee_r": "0",
    "kftc_bkpr": "390",
    "kftc_deal_bas_r": "390.22",
    "cur_nm": "사우디 리얄"
  },
  {
    "result": 1,
    "cur_unit": "SEK",
    "ttb": "156.63",
    "tts": "159.8",
    "deal_bas_r": "158.22",
    "bkpr": "158",
    "yy_efee_r": "0",
    "ten_dd_efee_r": "0",
    "kftc_bkpr": "158",
    "kftc_deal_bas_r": "158.22",
    "cur_nm": "스웨덴 크로나"
  },
  {
    "result": 1,
    "cur_unit": "SGD",
    "ttb": "1,135.57",
    "tts": "1,158.52",
    "deal_bas_r": "1,147.05",
    "bkpr": "1,147",
    "yy_efee_r": "0",
    "ten_dd_efee_r": "0",
    "kftc_bkpr": "1,147",
    "kftc_deal_bas_r": "1,147.05",
    "cur_nm": "싱가포르 달러"
  },
  {
    "result": 1,
    "cur_unit": "THB",
    "ttb": "46.08",
    "tts": "47.01",
    "deal_bas_r": "46.55",
    "bkpr": "46",
    "yy_efee_r": "0",
    "ten_dd_efee_r": "0",
    "kftc_bkpr": "46",
    "kftc_deal_bas_r": "46.55",
    "cur_nm": "태국 바트"
  },
  {
    "result": 1,
    "cur_unit": "USD",
    "ttb": "1,449.85",
    "tts": "1,479.14",
    "deal_bas_r": "1,464.5",
    "bkpr": "1,464",
    "yy_efee_r": "0",
    "ten_dd_efee_r": "0",
    "kftc_bkpr": "1,464",
    "kftc_deal_bas_r": "1,464.5",
    "cur_nm": "미국 달러"
  }
]
